HISTORY.txt
README.txt
setup.py
collective/__init__.py
collective.transform.txt2tags.egg-info/PKG-INFO
collective.transform.txt2tags.egg-info/SOURCES.txt
collective.transform.txt2tags.egg-info/dependency_links.txt
collective.transform.txt2tags.egg-info/entry_points.txt
collective.transform.txt2tags.egg-info/namespace_packages.txt
collective.transform.txt2tags.egg-info/not-zip-safe
collective.transform.txt2tags.egg-info/requires.txt
collective.transform.txt2tags.egg-info/top_level.txt
collective/transform/__init__.py
collective/transform/txt2tags/README.txt
collective/transform/txt2tags/__init__.py
collective/transform/txt2tags/browser.txt
collective/transform/txt2tags/configure.zcml
collective/transform/txt2tags/setuphandlers.py
collective/transform/txt2tags/tests.py
collective/transform/txt2tags/txt2tags.py
collective/transform/txt2tags/txt2tags_to_html.py
collective/transform/txt2tags/profiles/default/collective.transform.txt2tags.txt
collective/transform/txt2tags/profiles/default/metadata.xml
collective/transform/txt2tags/profiles/uninstall/collective.transform.txt2tags-uninstall.txt
docs/HISTORY.txt