Metadata-Version: 1.0
Name: collective.transform.txt2tags
Version: 1.1
Summary: txt2tags transform for Plone
Home-page: https://svn.plone.org/svn/collective/collective.transform.txt2tags
Author: Ales Zabala Alava (Shagi)
Author-email: shagi@gisa-elkartea.org
License: GPL
Keywords: Plone transform
Platform: UNKNOWN
Classifier: Framework :: Plone
Classifier: Programming Language :: Python
Classifier: Topic :: Software Development :: Libraries :: Python Modules
